{
  "type": "hexerei:mixingcauldron",
  "weather": "clear",
  "liquid": "lava",
  "ingredients": [
    {
      "item": "minecraft:netherite_ingot"
    },
    {
      "item": "minecraft:diamond"
    },
    {
      "item": "minecraft:iron_ingot"
    },
    {
      "item": "hexerei:mahogany_planks"
    },
    {
      "item": "hexerei:mahogany_planks"
    },
    {
      "item": "hexerei:mahogany_planks"
    },
    {
      "item": "minecraft:iron_ingot"
    },
    {
      "item": "minecraft:diamond"
    }
  ],
  "output": {
    "item": "hexerei:warhammer"
  },
  "liquidOutput": "lava",
  "fluidLevelsConsumed": 1
}


{
  "type": "minecraft:smithing",
  "base": {
    "item": "minecraft:diamond_hoe"
  },
  "addition": {
    "item": "minecraft:netherite_ingot"
  },
  "result": {
    "item": "minecraft:netherite_hoe"
  }
}